geihdanepy/__init__.py
geihdanepy/get.py
geihdanepy/utils.py
geihdanepy/txt_files/__init__.py
geihdanepy-0.2.3.dist-info/LICENSE
geihdanepy-0.2.3.dist-info/METADATA
geihdanepy-0.2.3.dist-info/WHEEL
geihdanepy-0.2.3.dist-info/top_level.txt
geihdanepy-0.2.3.dist-info/RECORD
