Metadata-Version: 2.1
Name: geihdanepy
Version: 0.2.3
Summary: Paquete de Python para usar las bases de datos de la GEIH del DANE.
Home-page: https://github.com/BautistaDavid/geihdanepy
Author: David Felipe Bauista
Author-email: dfbau2002@gmail.com
License: UNKNOWN
Project-URL: Documentation, https://github.com/BautistaDavid/geihdanepy
Project-URL: Bug Reports, https://github.com/BautistaDavid/geihdanepy/issues
Project-URL: Source Code, https://github.com/BautistaDavid/geihdanepy
Keywords: geih,pandas,data
Platform: UNKNOWN
Classifier: Development Status :: 5 - Production/Stable
Classifier: Intended Audience :: Developers
Classifier: Topic :: Software Development :: Build Tools
Classifier: Programming Language :: Python :: 3
Classifier: Programming Language :: Python :: 3.6
Classifier: Programming Language :: Python :: 3.7
Classifier: Programming Language :: Python :: 3.8
Classifier: Programming Language :: Python :: 3.9
Classifier: Programming Language :: Python :: 3 :: Only
Classifier: License :: OSI Approved :: MIT License
Classifier: Operating System :: OS Independent
Requires-Python: >=3.6
Provides-Extra: dev
Requires-Dist: check-manifest ; extra == 'dev'
